autotagger.py
autotagger-0.1.6.dist-info/DESCRIPTION.rst
autotagger-0.1.6.dist-info/METADATA
autotagger-0.1.6.dist-info/RECORD
autotagger-0.1.6.dist-info/WHEEL
autotagger-0.1.6.dist-info/entry_points.txt
autotagger-0.1.6.dist-info/metadata.json
autotagger-0.1.6.dist-info/top_level.txt
