Metadata-Version: 2.0
Name: autotagger
Version: 0.1.6
Summary: Tag .mp3 and .m4a audio files from iTunes data automatically.
Home-page: https://github.com/reorx/autotagger
Author: reorx
Author-email: novoreorx@gmail.com
License: UNKNOWN
Platform: UNKNOWN
Requires-Dist: mutagen
Requires-Dist: requests
